bioimageloader/__init__.py
bioimageloader/_experimentals.py
bioimageloader/_version.py
bioimageloader/base.py
bioimageloader/batch.py
bioimageloader/common.py
bioimageloader/config.py
bioimageloader/plots.py
bioimageloader/template.py
bioimageloader/transforms.py
bioimageloader/types.py
bioimageloader/utils.py
bioimageloader/collections/__init__.py
bioimageloader/collections/_bbbc002.py
bioimageloader/collections/_bbbc004.py
bioimageloader/collections/_bbbc006.py
bioimageloader/collections/_bbbc007.py
bioimageloader/collections/_bbbc007_nunet.py
bioimageloader/collections/_bbbc008.py
bioimageloader/collections/_bbbc009.py
bioimageloader/collections/_bbbc013.py
bioimageloader/collections/_bbbc014.py
bioimageloader/collections/_bbbc015.py
bioimageloader/collections/_bbbc016.py
bioimageloader/collections/_bbbc018.py
bioimageloader/collections/_bbbc018_nunet.py
bioimageloader/collections/_bbbc020.py
bioimageloader/collections/_bbbc021.py
bioimageloader/collections/_bbbc026.py
bioimageloader/collections/_bbbc030.py
bioimageloader/collections/_bbbc039.py
bioimageloader/collections/_bbbc041.py
bioimageloader/collections/_cellpose.py
bioimageloader/collections/_compath.py
bioimageloader/collections/_compath_nunet.py
bioimageloader/collections/_digitpath.py
bioimageloader/collections/_digitpath_nunet.py
bioimageloader/collections/_dorian.py
bioimageloader/collections/_dsb2018.py
bioimageloader/collections/_dsb2018_nunet.py
bioimageloader/collections/_frunet.py
bioimageloader/collections/_livecell.py
bioimageloader/collections/_murphylab.py
bioimageloader/collections/_murphylab_nunet.py
bioimageloader/collections/_s_bsst265.py
bioimageloader/collections/_stardist.py
bioimageloader/collections/_tnbc.py
bioimageloader/collections/_tnbc_nunet.py
bioimageloader/collections/_ucsb.py
bioimageloader/collections/_ucsb_nunet.py
bioimageloader/collections/minimal.py
bioimageloader-0.1.1.dist-info/LICENSE
bioimageloader-0.1.1.dist-info/METADATA
bioimageloader-0.1.1.dist-info/WHEEL
bioimageloader-0.1.1.dist-info/top_level.txt
bioimageloader-0.1.1.dist-info/RECORD
