Metadata-Version: 2.1
Name: bioimageloader
Version: 0.1.1
Summary: load bioimages for machine learning
Home-page: https://github.com/LaboratoryOpticsBiosciences/bioimageloader
Author: Seongbin Lim
Author-email: seongbin.lim@polytechnique.edu
Classifier: Development Status :: 3 - Alpha
Classifier: License :: OSI Approved :: BSD License
Classifier: Intended Audience :: Education
Classifier: Intended Audience :: Science/Research
Classifier: Programming Language :: Python :: 3
Classifier: Programming Language :: Python :: 3.8
Classifier: Programming Language :: Python :: 3.9
Classifier: Topic :: Scientific/Engineering
Classifier: Topic :: Scientific/Engineering :: Bio-Informatics
Classifier: Topic :: Scientific/Engineering :: Image Processing
Classifier: Topic :: Scientific/Engineering :: Artificial Intelligence
Requires-Python: >=3.8
License-File: LICENSE
Requires-Dist: numpy
Requires-Dist: scipy
Requires-Dist: Pillow
Requires-Dist: opencv-python-headless
Requires-Dist: tifffile
Requires-Dist: imagecodecs
Requires-Dist: albumentations
Requires-Dist: scikit-image
Requires-Dist: PyYAML
Requires-Dist: pycocotools
Requires-Dist: gimpformats
Provides-Extra: all
Requires-Dist: pre-commit ; extra == 'all'
Requires-Dist: mypy ; extra == 'all'
Requires-Dist: isort ; extra == 'all'
Requires-Dist: flake8 ; extra == 'all'
Requires-Dist: Sphinx (==4.5.0) ; extra == 'all'
Requires-Dist: numpydoc (==1.2.1) ; extra == 'all'
Requires-Dist: furo (==2022.4.7) ; extra == 'all'
Requires-Dist: nbsphinx (==0.8.8) ; extra == 'all'
Requires-Dist: sphinx-copybutton (==0.5.0) ; extra == 'all'
Requires-Dist: plotly ; extra == 'all'
Requires-Dist: scikit-learn ; extra == 'all'
Requires-Dist: gimpformats ; extra == 'all'
Requires-Dist: torch ; extra == 'all'
Requires-Dist: torchvision ; extra == 'all'
Provides-Extra: dev
Requires-Dist: pre-commit ; extra == 'dev'
Requires-Dist: mypy ; extra == 'dev'
Requires-Dist: isort ; extra == 'dev'
Requires-Dist: flake8 ; extra == 'dev'
Requires-Dist: Sphinx (==4.5.0) ; extra == 'dev'
Requires-Dist: numpydoc (==1.2.1) ; extra == 'dev'
Requires-Dist: furo (==2022.4.7) ; extra == 'dev'
Requires-Dist: nbsphinx (==0.8.8) ; extra == 'dev'
Requires-Dist: sphinx-copybutton (==0.5.0) ; extra == 'dev'
Requires-Dist: plotly ; extra == 'dev'
Requires-Dist: scikit-learn ; extra == 'dev'
Requires-Dist: gimpformats ; extra == 'dev'
Provides-Extra: tensorflow
Requires-Dist: tensorflow ; extra == 'tensorflow'
Provides-Extra: torch
Requires-Dist: torch ; extra == 'torch'
Requires-Dist: torchvision ; extra == 'torch'
